{
    "articles": [
        {
            "uuid": "b407e7e2-e7c3-4942-9672-9c3a916da9a8",
            "title": "Airbnb Stock: Q3 2025 Performance May Disappoint As Growth Normalizes (NASDAQ:ABNB)",
            "description": "Get insights on Airbnb's (ABNB) upcoming Q3'25 earnings, mixed travel demand, and investment outlook. Learn what to watch before the November 6 call.",
            "keywords": [
                "Airbnb",
                "Earnings",
                "Travel Demand"
            ],
            "snippet": "I am a full-time analyst interested in a wide range of stocks. With my unique insights and knowledge, I hope to provide other investors with a contrasting view ...",
            "url": "https://seekingalpha.com/article/4830641-airbnb-fq325-performance-may-disappoint-as-growth-normalizes",
            "image_url": "https://static.seekingalpha.com/cdn/s3/uploads/getty_images/2191725662/image_2191725662.jpg?io=getty-c-w1536",
            "language": "en",
            "published_at": "2025-10-17T04:20:00.000000Z",
            "source": "seekingalpha.com",
            "relevance_score": null,
            "entities": [
                {
                    "symbol": "ABNB",
                    "name": "Airbnb, Inc.",
                    "exchange": null,
                    "exchange_long": null,
                    "country": "us",
                    "type": "equity",
                    "industry": "Communication Services",
                    "match_score": 65.16946,
                    "sentiment_score": -0.0258,
                    "highlights": [
                        {
                            "highlight": "<em>Airbnb</em> Stock: Q3 2025 Performance May Disappoint As Growth Normalizes (<em>NASDAQ:ABNB</em>)",
                            "sentiment": -0.0258,
                            "highlighted_in": "title"
                        }
                    ]
                }
            ],
            "similar": [],
            "summary": "에어비앤비(ABNB)의 다가오는 3분기 실적 발표에 대한 통찰을 제공합니다. 혼재된 여행 수요와 투자 전망에 대한 분석을 포함하며, 11월 6일 컨퍼런스 콜 전에 주목해야 할 사항들을 다룹니다. 이 기사는 투자자들이 실적 발표를 앞두고 무엇을 준비해야 할지 알려줍니다.",
            "sentiment": 0.0
        },
        {
            "uuid": "c8ae0352-bffd-4911-972e-3ad9fa2651dd",
            "title": "[2310.09903] Integrating feature selection and regression methods with technical indicators for predicting Apple Inc. stock prices",
            "description": "Abstract page for arXiv paper 2310.09903: Integrating feature selection and regression methods with technical indicators for predicting Apple Inc. stock prices",
            "keywords": [
                "Apple Inc.",
                "주가 예측",
                "기술적 지표"
            ],
            "snippet": "",
            "url": "https://arxiv.org/abs/2310.09903",
            "image_url": "https://arxiv.org/static/browse/0.3.4/images/arxiv-logo-fb.png",
            "language": "en",
            "published_at": "2025-10-17T04:00:00.000000Z",
            "source": "arxiv.org",
            "relevance_score": null,
            "entities": [
                {
                    "symbol": "AAPL",
                    "name": "Apple Inc.",
                    "exchange": null,
                    "exchange_long": null,
                    "country": "us",
                    "type": "equity",
                    "industry": "Technology",
                    "match_score": 44.409164,
                    "sentiment_score": 0,
                    "highlights": [
                        {
                            "highlight": "[2310.09903] Integrating feature selection and regression methods with technical indicators for predicting <em>Apple</em> <em>Inc</em>. stock prices",
                            "sentiment": 0,
                            "highlighted_in": "title"
                        }
                    ]
                }
            ],
            "similar": [],
            "summary": "이 논문은 Apple Inc. 주가 예측을 위한 연구를 다룹니다. 특징 선택 및 회귀 분석 방법을 기술적 지표와 통합하여 활용합니다. 궁극적으로 주가 예측 모델의 성능 향상을 목표로 합니다.",
            "sentiment": 0.0
        }
    ],
    "trend_summary": {
        "title": "에어비앤비 실적과 애플 주가 전망, 시장의 복합적 신호",
        "summary": "에어비앤비의 견조한 실적은 여행 수요의 지속적인 강세를 시사하며, 이는 관련 섹터에 긍정적인 영향을 미칠 수 있습니다. 그러나 애플 Inc.의 향후 실적 및 주가 예측은 기술 섹터 전반의 투자 심리에 중요한 변수로 작용할 것입니다. 현재 시장 심리가 중립적인 만큼, 투자자께서는 개별 기업의 펀더멘털과 거시 경제 지표를 종합적으로 고려하여 신중한 접근을 권해드립니다.",
        "keywords": [
            "Airbnb",
            "Earnings",
            "Travel Demand",
            "Apple Inc.",
            "주가 예측"
        ]
    },
    "market_sentiment_score": 0.0,
    "nasdaq_data": {
        "labels": [
            "09-05",
            "09-08",
            "09-09",
            "09-10",
            "09-11",
            "09-12",
            "09-15",
            "09-16",
            "09-17",
            "09-18",
            "09-19",
            "09-22",
            "09-23",
            "09-24",
            "09-25",
            "09-26",
            "09-29",
            "09-30",
            "10-01",
            "10-02",
            "10-03",
            "10-06",
            "10-07",
            "10-08",
            "10-09",
            "10-10",
            "10-13",
            "10-14",
            "10-15",
            "10-16",
            "10-18",
            "10-19",
            "10-20",
            "10-21",
            "10-22",
            "10-23",
            "10-24"
        ],
        "historical": [
            [
                21700.39
            ],
            [
                21798.7
            ],
            [
                21879.49
            ],
            [
                21886.06
            ],
            [
                22043.07
            ],
            [
                22141.1
            ],
            [
                22348.75
            ],
            [
                22333.96
            ],
            [
                22261.33
            ],
            [
                22470.72
            ],
            [
                22631.48
            ],
            [
                22788.98
            ],
            [
                22573.47
            ],
            [
                22497.86
            ],
            [
                22384.7
            ],
            [
                22484.07
            ],
            [
                22591.15
            ],
            [
                22660.01
            ],
            [
                22755.16
            ],
            [
                22844.05
            ],
            [
                22780.51
            ],
            [
                22941.67
            ],
            [
                22788.36
            ],
            [
                23043.38
            ],
            [
                23024.63
            ],
            [
                22204.43
            ],
            [
                22694.61
            ],
            [
                22521.7
            ],
            [
                22670.08
            ],
            [
                22562.54
            ]
        ],
        "forecast": [
            null,
            null,
            null,
            null,
            null,
            null,
            null,
            null,
            null,
            null,
            null,
            null,
            null,
            null,
            null,
            null,
            null,
            null,
            null,
            null,
            null,
            null,
            null,
            null,
            null,
            null,
            null,
            null,
            null,
            null,
            22389.15,
            22540.62,
            22471.2,
            22510.72,
            22471.34,
            22438.93,
            22480.94
        ]
    },
    "kospi_data": {
        "labels": [
            "08-29",
            "09-01",
            "09-02",
            "09-03",
            "09-04",
            "09-05",
            "09-08",
            "09-09",
            "09-10",
            "09-11",
            "09-12",
            "09-15",
            "09-16",
            "09-17",
            "09-18",
            "09-19",
            "09-22",
            "09-23",
            "09-24",
            "09-25",
            "09-26",
            "09-29",
            "09-30",
            "10-01",
            "10-02",
            "10-10",
            "10-13",
            "10-14",
            "10-15",
            "10-16",
            "10-18",
            "10-19",
            "10-20",
            "10-21",
            "10-22",
            "10-23",
            "10-24"
        ],
        "historical": [
            [
                3186.01
            ],
            [
                3142.93
            ],
            [
                3172.35
            ],
            [
                3184.42
            ],
            [
                3200.83
            ],
            [
                3205.12
            ],
            [
                3219.59
            ],
            [
                3260.05
            ],
            [
                3314.53
            ],
            [
                3344.2
            ],
            [
                3395.54
            ],
            [
                3407.31
            ],
            [
                3449.62
            ],
            [
                3413.4
            ],
            [
                3461.3
            ],
            [
                3445.24
            ],
            [
                3468.65
            ],
            [
                3486.19
            ],
            [
                3472.14
            ],
            [
                3471.11
            ],
            [
                3386.05
            ],
            [
                3431.21
            ],
            [
                3424.6
            ],
            [
                3455.83
            ],
            [
                3549.21
            ],
            [
                3610.6
            ],
            [
                3584.55
            ],
            [
                3561.81
            ],
            [
                3657.28
            ],
            [
                3748.37
            ]
        ],
        "forecast": [
            null,
            null,
            null,
            null,
            null,
            null,
            null,
            null,
            null,
            null,
            null,
            null,
            null,
            null,
            null,
            null,
            null,
            null,
            null,
            null,
            null,
            null,
            null,
            null,
            null,
            null,
            null,
            null,
            null,
            null,
            3778.81,
            3773.06,
            3784.75,
            3822.77,
            3854.78,
            3866.63,
            3869.64
        ]
    },
    "fx_data": {
        "labels": [
            "09-05",
            "09-08",
            "09-09",
            "09-10",
            "09-11",
            "09-12",
            "09-15",
            "09-16",
            "09-17",
            "09-18",
            "09-19",
            "09-22",
            "09-23",
            "09-24",
            "09-25",
            "09-26",
            "09-29",
            "09-30",
            "10-01",
            "10-02",
            "10-03",
            "10-06",
            "10-07",
            "10-08",
            "10-09",
            "10-10",
            "10-13",
            "10-14",
            "10-15",
            "10-16",
            "10-18",
            "10-19",
            "10-20",
            "10-21",
            "10-22",
            "10-23",
            "10-24"
        ],
        "historical": [
            [
                1392.06
            ],
            [
                1385.51
            ],
            [
                1385.72
            ],
            [
                1387.25
            ],
            [
                1387.2
            ],
            [
                1389.5
            ],
            [
                1393.7
            ],
            [
                1385.01
            ],
            [
                1377.64
            ],
            [
                1378.69
            ],
            [
                1386.75
            ],
            [
                1396.23
            ],
            [
                1389.39
            ],
            [
                1391.85
            ],
            [
                1403.65
            ],
            [
                1408.92
            ],
            [
                1408.71
            ],
            [
                1399.33
            ],
            [
                1403.15
            ],
            [
                1401.82
            ],
            [
                1405.63
            ],
            [
                1406.06
            ],
            [
                1409.92
            ],
            [
                1414.57
            ],
            [
                1422.52
            ],
            [
                1421.51
            ],
            [
                1429.03
            ],
            [
                1426.07
            ],
            [
                1429.43
            ],
            [
                1420.09
            ]
        ],
        "forecast": [
            null,
            null,
            null,
            null,
            null,
            null,
            null,
            null,
            null,
            null,
            null,
            null,
            null,
            null,
            null,
            null,
            null,
            null,
            null,
            null,
            null,
            null,
            null,
            null,
            null,
            null,
            null,
            null,
            null,
            null,
            1422.18,
            1420.6,
            1424.19,
            1420.98,
            1421.87,
            1420.48,
            1422.41
        ]
    },
    "last_updated": "2025-10-17 00:00:00"
}